mercedesmejsonpy/Exceptions.py
mercedesmejsonpy/__init__.py
mercedesmejsonpy/controller.py
mercedesmejsonpy/oauth.py
mercedesmejsonpy-0.2.4.dist-info/METADATA
mercedesmejsonpy-0.2.4.dist-info/RECORD
mercedesmejsonpy-0.2.4.dist-info/WHEEL
mercedesmejsonpy-0.2.4.dist-info/top_level.txt
