Metadata-Version: 2.1
Name: mercedesmejsonpy
Version: 0.2.4
Summary: A library to work with Mercedes Connected Vehicle API.
Home-page: UNKNOWN
Author: Rene Nulsch
Author-email: github.mercedesmejsonpy@nulsch.de
License: WTFPL
Platform: UNKNOWN
Classifier: Intended Audience :: Developers
Classifier: Operating System :: OS Independent
Classifier: Programming Language :: Python :: 3
Classifier: Programming Language :: Python :: 3.4
Classifier: Programming Language :: Python :: 3.5
Classifier: Topic :: Internet
Requires-Python: >=3
Requires-Dist: requests (>=2.18.4)
